odoo/addons/pattern_import_export_xlsx/README.rst
odoo/addons/pattern_import_export_xlsx/__init__.py
odoo/addons/pattern_import_export_xlsx/__manifest__.py
odoo/addons/pattern_import_export_xlsx/demo/demo.xml
odoo/addons/pattern_import_export_xlsx/migrations/12.0.3.0.0/post-migrate.py
odoo/addons/pattern_import_export_xlsx/models/__init__.py
odoo/addons/pattern_import_export_xlsx/models/pattern_config.py
odoo/addons/pattern_import_export_xlsx/models/pattern_file.py
odoo/addons/pattern_import_export_xlsx/readme/CONFIGURE.rst
odoo/addons/pattern_import_export_xlsx/readme/CONTRIBUTORS.rst
odoo/addons/pattern_import_export_xlsx/readme/DESCRIPTION.rst
odoo/addons/pattern_import_export_xlsx/readme/USAGE.rst
odoo/addons/pattern_import_export_xlsx/static/description/index.html
odoo/addons/pattern_import_export_xlsx/tests/__init__.py
odoo/addons/pattern_import_export_xlsx/tests/test_pattern_export.py
odoo/addons/pattern_import_export_xlsx/tests/test_pattern_import.py
odoo/addons/pattern_import_export_xlsx/tests/fixtures/example.partners.failed.xlsx
odoo/addons/pattern_import_export_xlsx/tests/fixtures/example.partners.ok.xlsx
odoo/addons/pattern_import_export_xlsx/tests/fixtures/example.partners.parent.xlsx
odoo/addons/pattern_import_export_xlsx/tests/fixtures/example.partners.too_many_error.xlsx
odoo/addons/pattern_import_export_xlsx/tests/fixtures/example.users.descriptive.ok.xlsx
odoo/addons/pattern_import_export_xlsx/tests/fixtures/example.users.failed.xlsx
odoo/addons/pattern_import_export_xlsx/tests/fixtures/example.users.ok.xlsx
odoo/addons/pattern_import_export_xlsx/views/pattern_config.xml
odoo12_addon_pattern_import_export_xlsx-12.0.5.0.0.dist-info/METADATA
odoo12_addon_pattern_import_export_xlsx-12.0.5.0.0.dist-info/WHEEL
odoo12_addon_pattern_import_export_xlsx-12.0.5.0.0.dist-info/top_level.txt
odoo12_addon_pattern_import_export_xlsx-12.0.5.0.0.dist-info/RECORD
